{
  "body": "{\"temp\":0.5,\"icon\":\"SNOW\",\"weather_desc\":\"Snow at times\",\"feels_like\":-4.6,\"wind_direction\":341,\"wind_speed\":17,\"wind_gust\":30,\"overnight_low\":-0.1,\"overnight_low_time\":\"06:14pm\",\"daytime_high\":0.6,\"daytime_high_time\":\"08:58pm\",\"strongest_wind\":65,\"strongest_wind_time\":\"02:24am\",\"precip_since_9_am\":57.2,\"last_updated\":\"2026-07-13T05:40:00+10:00\",\"last_updated_formatted\":\"13 Jul 2026 05:40am\",\"snow_report\":{\"resort_rating\":\"Limited cover\",\"average_natural\":26,\"average_made\":56,\"wheel_chains_required\":\"No\",\"snow_last_24_hours\":14,\"snow_last_48_hours\":null,\"snow_last_72_hours\":null,\"snow_season_total\":null,\"resort_cover\":\"Fair\",\"last_snowfall_date\":\"12 Jul 2026\",\"weather_description\":\"<p>Fresh snow overnight, with more forecast through the day.<\\/p>\"},\"open_terrain_parks_count\":0,\"all_terrain_parks_count\":6,\"open_trails_count\":4,\"all_trails_count\":81,\"open_lifts_count\":0,\"all_lifts_count\":19}",
  "capturedAt": "2026-07-12T19:59:05.422620Z",
  "contentType": "application/json",
  "httpStatus": 200,
  "normalizedRecordIds": [
    "de33d02a-f6c5-45b5-ba7d-17e9b53b5f5a"
  ],
  "parserVersion": 1,
  "payloadHash": "bfc232be3100231c2caf271eaaa5e901378358a21ce4b1d5aacec9b07f1a340d",
  "responseAt": "2026-07-12T19:59:06.206592Z",
  "url": "https://api.mtbuller.com.au/api/weather/widget"
}
