{
  "body": "{\"temp\":2.8,\"icon\":\"SUNNY\",\"weather_desc\":\"Sunny\",\"feels_like\":-0.3,\"wind_direction\":0,\"wind_speed\":0,\"wind_gust\":0,\"overnight_low\":-2.4,\"overnight_low_time\":\"03:22am\",\"daytime_high\":4.5,\"daytime_high_time\":\"12:18pm\",\"strongest_wind\":0,\"strongest_wind_time\":\"03:20pm\",\"precip_since_9_am\":0,\"last_updated\":\"2026-07-15T15:20:00+10:00\",\"last_updated_formatted\":\"15 Jul 2026 03:20pm\",\"snow_report\":{\"resort_rating\":\"Limited cover\",\"average_natural\":21,\"average_made\":54,\"wheel_chains_required\":\"No\",\"snow_last_24_hours\":0,\"snow_last_48_hours\":null,\"snow_last_72_hours\":null,\"snow_season_total\":null,\"resort_cover\":\"Fair\",\"last_snowfall_date\":\"12 Jul 2026\",\"weather_description\":\"<p>Sunshine and views are back. Enjoy groomed turns on a softening fair to good cover on runs open.<\\/p>\"},\"open_terrain_parks_count\":1,\"all_terrain_parks_count\":6,\"open_trails_count\":4,\"all_trails_count\":81,\"open_lifts_count\":7,\"all_lifts_count\":19}",
  "capturedAt": "2026-07-15T05:36:34.334476Z",
  "contentType": "application/json",
  "httpStatus": 200,
  "normalizedRecordIds": [
    "7f74add8-6372-4781-aa78-2136cdd32866"
  ],
  "parserVersion": 1,
  "payloadHash": "4f7e6c1ade69dd5f0ffeecf96e49519ac782d7c79bd6ca1997b1ab611b474bc8",
  "responseAt": "2026-07-15T05:36:35.581366Z",
  "url": "https://api.mtbuller.com.au/api/weather/widget"
}
