{
  "body": "<?xml version=\"1.0\" encoding=\"UTF-8\" standalone=\"no\" ?>\r\n<SnowReport>\r\n\t<_LastUpdated>2026-07-21T06:35:18</_LastUpdated>\r\n\t<TwentyFourHourSnowfall>0</TwentyFourHourSnowfall>\r\n\t<CurrentSnowdepth>41</CurrentSnowdepth>\r\n\t<AvSnowdepthinSnowmakingAreas>107</AvSnowdepthinSnowmakingAreas>\r\n\t<AvSnowdepthLastMeasuredOn>20/07/2026</AvSnowdepthLastMeasuredOn>\r\n\t<DateofLastSnowfall>14/07/2026</DateofLastSnowfall>\r\n\t<SevenDaySnowfall>0</SevenDaySnowfall>\r\n\t<SeasonToDateSnowfall>96</SeasonToDateSnowfall>\r\n\t<Snowmaking>In Progress</Snowmaking>\r\n\t<WeatherConditionsasat6AM></WeatherConditionsasat6AM>\r\n\t<Temperature>2.7</Temperature>\r\n\t<OvernightMin>2.7</OvernightMin>\r\n\t<ForecastMax>5</ForecastMax>\r\n\t<Wind>Moderate 26-40 km/h</Wind>\r\n\t<WindDirection>N</WindDirection>\r\n\t<Precipitation>None</Precipitation>\r\n\t<ExpectedVisibility>Excellent</ExpectedVisibility>\r\n\t<ExpectedCloudCover>Sunny</ExpectedCloudCover>\r\n\t<Forecast>Mostly sunny. Winds north to northwesterly 25 to 35 km/h increasing to 30 to 40 km/h in the late evening.</Forecast>\r\n\t<ResortReportHeadline>Sun, Snowmaking and Heavenly Valley Opened Yesterday!</ResortReportHeadline>\r\n\t<ResortReport>&lt;p&gt;It&apos;ll be another cracker of a day on the hill!&amp;nbsp; The stars are shining and the snowguns are pumping it out thanks to the very low humidity all night.&amp;nbsp; The current temp is 2.7 degrees, heading for a top of 5 degrees and the wind is a moderate northerly which may increase later in the day.&amp;nbsp;&amp;nbsp;&lt;/p&gt;&lt;p&gt;I expect the snowmaking will make for good turns on the groomers this morning before some zones get scraped back to the hard base underneath.&amp;nbsp; The sunniest of aspects may soften for spring like turns as the day warms but the shaded and south facing slopes will probably stay very firm and slick for the day.&amp;nbsp;&amp;nbsp;&lt;/p&gt;&lt;p&gt;Heavenly Valley lift will be spinning once the patrol have completed their assessments, but the area is ONLY suitable for ADVANCED and EXPERT skiers and riders.&amp;nbsp; The cover is thin and the surface will likely remain icy on most runs for the day. The Extreme Area is Closed for ice hazard.&amp;nbsp; And DO NOT ATTEMPT to retrieve dropped equipment from any closed or out of bounds areas.&amp;nbsp; There is a dangerous sliding hazard out there at the moment.&lt;/p&gt;&lt;p&gt;Slap on the screen, stick to the open areas and have a beaut day in the sun.&amp;nbsp;&lt;/p&gt;&lt;p&gt;Cheers Bill&lt;/p&gt;</ResortReport>\r\n\t<HideReportEDMWeb>False</HideReportEDMWeb>\r\n\t<LiftsOpen></LiftsOpen>\r\n\t<LiftsStandby></LiftsStandby>\r\n\t<LiftsClosed></LiftsClosed>\r\n\t<RunsOpen></RunsOpen>\r\n\t<RunsGroomed></RunsGroomed>\r\n\t<RunsSnowmaking>5</RunsSnowmaking>\r\n\t<TerrainParks></TerrainParks>\r\n\t<Backcountry>21 July 2026&#13;&#10;&#13;&#10;There is a significant sliding hazard in the backcountry again today, plus the cover is thin, becoming more marginal the lower you go. The sunniest of aspects may soften for spring-like turns as the day warms, but shaded and south-facing slopes will likely stay very icy and dangerous for the day.  Take Care. </Backcountry>\r\n\t<Avalanche></Avalanche>\r\n\t<HeliLink>Closed</HeliLink>\r\n</SnowReport>\r\n",
  "capturedAt": "2026-07-20T21:37:56.614207Z",
  "contentType": "text/xml",
  "httpStatus": 200,
  "normalizedRecordIds": [
    "b62f7d6c-069a-4eb0-a31c-86471838a1e0"
  ],
  "parserVersion": 1,
  "payloadHash": "b7c7b708a831fe68099d729fd929a9f5c67b230607971cdf7ef93b627b7dbe3e",
  "responseAt": "2026-07-20T21:37:57.391708Z",
  "url": "https://snowreport.mthotham.com.au/resources/SnowReport.xml"
}
